[
    {
        "key": "datr",
        "value": "Vrh8aUGW0Ul8wp11jfH7hLs4",
        "domain": "facebook.com",
        "path": "/",
        "hostOnly": false,
        "creation": "2026-02-03T11:21:29.083Z",
        "lastAccessed": "2026-02-03T11:21:29.083Z"
    },
    {
        "key": "sb",
        "value": "Vrh8aQAkqd9D5JZcV-uy1Mvd",
        "domain": "facebook.com",
        "path": "/",
        "hostOnly": false,
        "creation": "2026-02-03T11:21:29.083Z",
        "lastAccessed": "2026-02-03T11:21:29.083Z"
    },
    {
        "key": "dpr",
        "value": "2.214021682739258",
        "domain": "facebook.com",
        "path": "/",
        "hostOnly": false,
        "creation": "2026-02-03T11:21:29.083Z",
        "lastAccessed": "2026-02-03T11:21:29.083Z"
    },
    {
        "key": "ps_l",
        "value": "1",
        "domain": "facebook.com",
        "path": "/",
        "hostOnly": false,
        "creation": "2026-02-03T11:21:29.083Z",
        "lastAccessed": "2026-02-03T11:21:29.083Z"
    },
    {
        "key": "ps_n",
        "value": "1",
        "domain": "facebook.com",
        "path": "/",
        "hostOnly": false,
        "creation": "2026-02-03T11:21:29.083Z",
        "lastAccessed": "2026-02-03T11:21:29.083Z"
    },
    {
        "key": "locale",
        "value": "en_GB",
        "domain": "facebook.com",
        "path": "/",
        "hostOnly": false,
        "creation": "2026-02-03T11:21:29.083Z",
        "lastAccessed": "2026-02-03T11:21:29.083Z"
    },
    {
        "key": "wd",
        "value": "775x1459",
        "domain": "facebook.com",
        "path": "/",
        "hostOnly": false,
        "creation": "2026-02-03T11:21:29.083Z",
        "lastAccessed": "2026-02-03T11:21:29.083Z"
    },
    {
        "key": "c_user",
        "value": "61578237884017",
        "domain": "facebook.com",
        "path": "/",
        "hostOnly": false,
        "creation": "2026-02-03T11:21:29.083Z",
        "lastAccessed": "2026-02-03T11:21:29.083Z"
    },
    {
        "key": "fr",
        "value": "1QBlKlkgq81QntBJI.AWcrwmwUBqNd8wFyZkH5SRZWDyIAuSJFkO7SzyjFitBs4LGNDV0.BpgdZX..AAA.0.0.BpgdZX.AWfCUFnYZiF74_3Lh1_4qO7kgmM",
        "domain": "facebook.com",
        "path": "/",
        "hostOnly": false,
        "creation": "2026-02-03T11:21:29.083Z",
        "lastAccessed": "2026-02-03T11:21:29.083Z"
    },
    {
        "key": "xs",
        "value": "34%3AfyEQ4kFBHxcKnQ%3A2%3A1770116690%3A-1%3A-1%3A%3AAcxPYjkqMSUovuq7b39uI8dYYSRaJz5Y8nJ1eA364g",
        "domain": "facebook.com",
        "path": "/",
        "hostOnly": false,
        "creation": "2026-02-03T11:21:29.083Z",
        "lastAccessed": "2026-02-03T11:21:29.083Z"
    },
    {
        "key": "presence",
        "value": "C%7B%22t3%22%3A%5B%5D%2C%22utc3%22%3A1770117679704%2C%22v%22%3A1%7D",
        "domain": "facebook.com",
        "path": "/",
        "hostOnly": false,
        "creation": "2026-02-03T11:21:29.083Z",
        "lastAccessed": "2026-02-03T11:21:29.083Z"
    }
        ]
